odoo8_addon_l10n_it_fatturapa-8.0.3.0.3-nspkg.pth
odoo_addons/l10n_it_fatturapa/README.rst
odoo_addons/l10n_it_fatturapa/__init__.py
odoo_addons/l10n_it_fatturapa/__openerp__.py
odoo_addons/l10n_it_fatturapa/bindings/__init__.py
odoo_addons/l10n_it_fatturapa/bindings/_ds.py
odoo_addons/l10n_it_fatturapa/bindings/binding.py
odoo_addons/l10n_it_fatturapa/bindings/fatturapa.py
odoo_addons/l10n_it_fatturapa/bindings/readme.md
odoo_addons/l10n_it_fatturapa/bindings/xsd/Schema_del_file_xml_FatturaPA_versione_1.2.1.xsd
odoo_addons/l10n_it_fatturapa/bindings/xsd/Schema_del_file_xml_FatturaPA_versione_1.2.1.xsd.diff
odoo_addons/l10n_it_fatturapa/controllers/__init__.py
odoo_addons/l10n_it_fatturapa/controllers/main.py
odoo_addons/l10n_it_fatturapa/data/FoglioStileAssoSoftware_v1.1.xsl
odoo_addons/l10n_it_fatturapa/data/fatturaordinaria_v1.2.1.xsl
odoo_addons/l10n_it_fatturapa/data/fatturapa_data.xml
odoo_addons/l10n_it_fatturapa/data/welfare.fund.type.csv
odoo_addons/l10n_it_fatturapa/demo/account_invoice_fatturapa.xml
odoo_addons/l10n_it_fatturapa/i18n/am.po
odoo_addons/l10n_it_fatturapa/i18n/ar.po
odoo_addons/l10n_it_fatturapa/i18n/bg.po
odoo_addons/l10n_it_fatturapa/i18n/bs.po
odoo_addons/l10n_it_fatturapa/i18n/ca.po
odoo_addons/l10n_it_fatturapa/i18n/cs.po
odoo_addons/l10n_it_fatturapa/i18n/da.po
odoo_addons/l10n_it_fatturapa/i18n/de.po
odoo_addons/l10n_it_fatturapa/i18n/el_GR.po
odoo_addons/l10n_it_fatturapa/i18n/en_GB.po
odoo_addons/l10n_it_fatturapa/i18n/es.po
odoo_addons/l10n_it_fatturapa/i18n/es_AR.po
odoo_addons/l10n_it_fatturapa/i18n/es_CL.po
odoo_addons/l10n_it_fatturapa/i18n/es_CO.po
odoo_addons/l10n_it_fatturapa/i18n/es_CR.po
odoo_addons/l10n_it_fatturapa/i18n/es_DO.po
odoo_addons/l10n_it_fatturapa/i18n/es_EC.po
odoo_addons/l10n_it_fatturapa/i18n/es_ES.po
odoo_addons/l10n_it_fatturapa/i18n/es_MX.po
odoo_addons/l10n_it_fatturapa/i18n/es_PE.po
odoo_addons/l10n_it_fatturapa/i18n/es_PY.po
odoo_addons/l10n_it_fatturapa/i18n/es_VE.po
odoo8_addon_l10n_it_fatturapa-8.0.3.0.3.dist-info/METADATA
odoo8_addon_l10n_it_fatturapa-8.0.3.0.3.dist-info/WHEEL
odoo8_addon_l10n_it_fatturapa-8.0.3.0.3.dist-info/namespace_packages.txt
odoo8_addon_l10n_it_fatturapa-8.0.3.0.3.dist-info/top_level.txt
odoo8_addon_l10n_it_fatturapa-8.0.3.0.3.dist-info/RECORD
